tanat_cli_preset/__init__.py
tanat_cli_preset/utils.py
tanat_cli_preset/version.py
tanat_cli_preset/config/config_admissions.yaml
tanat_cli_preset/config/config_mvad.yaml
tanat_cli_preset/config/workenv/workenv_admissions.yaml
tanat_cli_preset/config/workenv/workenv_mvad.yaml
tanat_cli_preset/config/workenv/loaders/example/admissions.yaml
tanat_cli_preset/config/workenv/loaders/example/mvad.yaml
tanat_cli_preset/config/workenv/sequence_pools/example/admissions.yaml
tanat_cli_preset/config/workenv/sequence_pools/example/mvad.yaml
tanat_cli_preset/config/workflow/admissions.yaml
tanat_cli_preset/config/workflow/mvad.yaml
tanat_cli_preset-0.2.0.dist-info/METADATA
tanat_cli_preset-0.2.0.dist-info/WHEEL
tanat_cli_preset-0.2.0.dist-info/licenses/LICENSE.txt
tanat_cli_preset-0.2.0.dist-info/RECORD
