Metadata-Version: 2.4
Name: TanaT-CLI-preset
Version: 0.2.0
Summary: A library for TanaT CLI commands presets.
Project-URL: Homepage, https://gitlab.inria.fr/tanat/core/tanat-cli-preset
Project-URL: Source, https://gitlab.inria.fr/tanat/core/tanat-cli-preset.git
Project-URL: Documentation, https://tanat.gitlabpages.inria.fr/tanat
Project-URL: Issues, https://gitlab.inria.fr/tanat/core/tanat/-/issues
Author-email: Arnaud Duvermy <arnaud.duvermy@inria.fr>, Thomas Guyet <thomas.guyet@inria.fr>
License: MIT License
License-File: LICENSE.txt
Classifier: License :: OSI Approved :: MIT License
Classifier: Operating System :: OS Independent
Classifier: Programming Language :: Python :: 3
Requires-Python: >=3.7
